{"name":"build-javascript","namedChunkGroups":{"app":{"name":"app","assets":[{"name":"webpack-runtime-dde32edde3daf6318609.js","size":4964},{"name":"framework-8f5d29e3deec887177fc.js","size":140755},{"name":"app-60db4985e1519bf7b5a3.js","size":62432}],"filteredAssets":0,"assetsSize":208151,"filteredAuxiliaryAssets":3,"auxiliaryAssetsSize":602954},"component---src-pages-about-jsx":{"name":"component---src-pages-about-jsx","assets":[{"name":"styles.98a01fb3cee550da1756.css","size":323806},{"name":"component---src-pages-about-jsx-e3c45ad38997d2a9a595.js","size":8190}],"filteredAssets":0,"assetsSize":331996,"filteredAuxiliaryAssets":1,"auxiliaryAssetsSize":15290},"component---src-pages-analises-jsx":{"name":"component---src-pages-analises-jsx","assets":[{"name":"styles.98a01fb3cee550da1756.css","size":323806},{"name":"component---src-pages-analises-jsx-edc87173bad81a1d4cd7.js","size":7234}],"filteredAssets":0,"assetsSize":331040,"filteredAuxiliaryAssets":1,"auxiliaryAssetsSize":18636},"component---src-pages-index-jsx":{"name":"component---src-pages-index-jsx","assets":[{"name":"styles.98a01fb3cee550da1756.css","size":323806},{"name":"component---src-pages-index-jsx-3bfbd93fa9e4bce7883b.js","size":78715}],"filteredAssets":0,"assetsSize":402521,"filteredAuxiliaryAssets":1,"auxiliaryAssetsSize":295200},"component---src-pages-news-jsx":{"name":"component---src-pages-news-jsx","assets":[{"name":"styles.98a01fb3cee550da1756.css","size":323806},{"name":"component---src-pages-news-jsx-c7d88d603c9eb666b166.js","size":8746}],"filteredAssets":0,"assetsSize":332552,"filteredAuxiliaryAssets":1,"auxiliaryAssetsSize":19112}},"assetsByChunkName":{"app":["webpack-runtime-dde32edde3daf6318609.js","framework-8f5d29e3deec887177fc.js","app-60db4985e1519bf7b5a3.js"],"component---src-pages-about-jsx":["styles.98a01fb3cee550da1756.css","component---src-pages-about-jsx-e3c45ad38997d2a9a595.js"],"component---src-pages-analises-jsx":["styles.98a01fb3cee550da1756.css","component---src-pages-analises-jsx-edc87173bad81a1d4cd7.js"],"component---src-pages-index-jsx":["styles.98a01fb3cee550da1756.css","component---src-pages-index-jsx-3bfbd93fa9e4bce7883b.js"],"component---src-pages-news-jsx":["styles.98a01fb3cee550da1756.css","component---src-pages-news-jsx-c7d88d603c9eb666b166.js"]},"childAssetsByChunkName":{}}